LICENSE
MANIFEST.in
README.md
pyproject.toml
setup.py
jboc/__init__.py
jboc/__version__.py
jboc/_main.py
jboc/py.typed
jboc.egg-info/PKG-INFO
jboc.egg-info/SOURCES.txt
jboc.egg-info/dependency_links.txt
jboc.egg-info/top_level.txt