Metadata-Version: 2.1
Name: jboc
Version: 0.1.0
Summary: No dependencies, no paradigm - Just a Bunch Of Code
Home-page: https://github.com/maxme1/jboc
Author: maxme1
Author-email: maxs987@gmail.com
License: MIT
Download-URL: https://github.com/maxme1/jboc/archive/v0.1.0.tar.gz
Keywords: utils,misc
Platform: UNKNOWN
Classifier: Development Status :: 5 - Production/Stable
Classifier: License :: OSI Approved :: MIT License
Classifier: Programming Language :: Python :: 3
Classifier: Programming Language :: Python :: 3.6
Classifier: Programming Language :: Python :: 3.7
Classifier: Programming Language :: Python :: 3.8
Classifier: Programming Language :: Python :: 3.9
Classifier: Programming Language :: Python :: 3.10
Classifier: Programming Language :: Python :: 3.11
Classifier: Programming Language :: Python :: 3 :: Only
Requires-Python: >=3.6
License-File: LICENSE
